{"search":["/pack/search.ef1f425f2847cf3a8ed6.js","/pack/search.ef1f425f2847cf3a8ed6.js.map"],"ebook":["/pack/ebook.ef1f425f2847cf3a8ed6.js","/pack/ebook.ef1f425f2847cf3a8ed6.js.map"],"tutorial":["/pack/tutorial.ef1f425f2847cf3a8ed6.js","/pack/tutorial.ef1f425f2847cf3a8ed6.js.map"],"footer":["/pack/footer.ef1f425f2847cf3a8ed6.js","/pack/footer.ef1f425f2847cf3a8ed6.js.map"],"angular":["/pack/angular.ef1f425f2847cf3a8ed6.js","/pack/angular.ef1f425f2847cf3a8ed6.js.map"],"nodejsScreencast":["/pack/nodejsScreencast.ef1f425f2847cf3a8ed6.js","/pack/nodejsScreencast.ef1f425f2847cf3a8ed6.js.map"],"head":["/pack/head.ef1f425f2847cf3a8ed6.js","/pack/head.ef1f425f2847cf3a8ed6.js.map"],"authClient":["/pack/authClient-7.ef1f425f2847cf3a8ed6.js","/pack/authClient-7.ef1f425f2847cf3a8ed6.js.map"],"profile":["/pack/profile.ef1f425f2847cf3a8ed6.js","/pack/profile.ef1f425f2847cf3a8ed6.js.map"],"styles":["/pack/styles.ef1f425f2847cf3a8ed6.js","/pack/styles.95cc3254257b33ba078e043ed6b3b2f1.css","/pack/styles.ef1f425f2847cf3a8ed6.js.map","/pack/styles.95cc3254257b33ba078e043ed6b3b2f1.css.map"],"quiz":["/pack/quiz.ef1f425f2847cf3a8ed6.js","/pack/quiz.ef1f425f2847cf3a8ed6.js.map"]}