{"search":["/pack/search.24a89ea91979b213affb.js","/pack/search.24a89ea91979b213affb.js.map"],"ebook":["/pack/ebook.24a89ea91979b213affb.js","/pack/ebook.24a89ea91979b213affb.js.map"],"tutorial":["/pack/tutorial.24a89ea91979b213affb.js","/pack/tutorial.24a89ea91979b213affb.js.map"],"footer":["/pack/footer.24a89ea91979b213affb.js","/pack/footer.24a89ea91979b213affb.js.map"],"angular":["/pack/angular.24a89ea91979b213affb.js","/pack/angular.24a89ea91979b213affb.js.map"],"nodejsScreencast":["/pack/nodejsScreencast.24a89ea91979b213affb.js","/pack/nodejsScreencast.24a89ea91979b213affb.js.map"],"head":["/pack/head.24a89ea91979b213affb.js","/pack/head.24a89ea91979b213affb.js.map"],"authClient":["/pack/authClient-7.24a89ea91979b213affb.js","/pack/authClient-7.24a89ea91979b213affb.js.map"],"profile":["/pack/profile.24a89ea91979b213affb.js","/pack/profile.24a89ea91979b213affb.js.map"],"styles":["/pack/styles.24a89ea91979b213affb.js","/pack/styles.a33bfb0adea9e51590fad517eafb5163.css","/pack/styles.24a89ea91979b213affb.js.map","/pack/styles.a33bfb0adea9e51590fad517eafb5163.css.map"],"quiz":["/pack/quiz.24a89ea91979b213affb.js","/pack/quiz.24a89ea91979b213affb.js.map"]}