{"search":["/pack/search.32a1f8398917f38926af.js","/pack/search.32a1f8398917f38926af.js.map"],"ebook":["/pack/ebook.32a1f8398917f38926af.js","/pack/ebook.32a1f8398917f38926af.js.map"],"tutorial":["/pack/tutorial.32a1f8398917f38926af.js","/pack/tutorial.32a1f8398917f38926af.js.map"],"footer":["/pack/footer.32a1f8398917f38926af.js","/pack/footer.32a1f8398917f38926af.js.map"],"angular":["/pack/angular.32a1f8398917f38926af.js","/pack/angular.32a1f8398917f38926af.js.map"],"nodejsScreencast":["/pack/nodejsScreencast.32a1f8398917f38926af.js","/pack/nodejsScreencast.32a1f8398917f38926af.js.map"],"head":["/pack/head.32a1f8398917f38926af.js","/pack/head.9910b900b2945dedcfdeff7fe2d8e67e.css","/pack/head.32a1f8398917f38926af.js.map","/pack/head.9910b900b2945dedcfdeff7fe2d8e67e.css.map"],"authClient":["/pack/authClient-7.32a1f8398917f38926af.js","/pack/authClient-7.32a1f8398917f38926af.js.map"],"profile":["/pack/profile.32a1f8398917f38926af.js","/pack/profile.32a1f8398917f38926af.js.map"],"quiz":["/pack/quiz.32a1f8398917f38926af.js","/pack/quiz.ccccd05549bb091f981019760cb669da.css","/pack/quiz.32a1f8398917f38926af.js.map","/pack/quiz.ccccd05549bb091f981019760cb669da.css.map"],"about":["/pack/about.32a1f8398917f38926af.js","/pack/about.bb5ef126815e129b6d032ee090b0cfc7.css","/pack/about.32a1f8398917f38926af.js.map","/pack/about.bb5ef126815e129b6d032ee090b0cfc7.css.map"],"ebookExtras":["/pack/ebookExtras-13.32a1f8398917f38926af.js","/pack/ebookExtras-13.32a1f8398917f38926af.js.map"],"courses":["/pack/courses.32a1f8398917f38926af.js","/pack/courses.32a1f8398917f38926af.js.map"]}