{"search":["/pack/search.48bffc950a9d6db0a82b.js","/pack/search.48bffc950a9d6db0a82b.js.map"],"coursesCourse":["/pack/coursesCourse.48bffc950a9d6db0a82b.js","/pack/coursesCourse.48bffc950a9d6db0a82b.js.map"],"authClient":["/pack/authClient-2.48bffc950a9d6db0a82b.js","/pack/authClient-2.48bffc950a9d6db0a82b.js.map"],"footer":["/pack/footer.48bffc950a9d6db0a82b.js","/pack/footer.48bffc950a9d6db0a82b.js.map"],"angular":["/pack/angular.48bffc950a9d6db0a82b.js","/pack/angular.48bffc950a9d6db0a82b.js.map"],"tutorial":["/pack/tutorial.48bffc950a9d6db0a82b.js","/pack/tutorial.48bffc950a9d6db0a82b.js.map"],"ebookExtras":["/pack/ebookExtras-6.48bffc950a9d6db0a82b.js","/pack/ebookExtras-6.48bffc950a9d6db0a82b.js.map"],"coursesSignup":["/pack/coursesSignup.48bffc950a9d6db0a82b.js","/pack/coursesSignup.48bffc950a9d6db0a82b.js.map"],"ebook":["/pack/ebook.48bffc950a9d6db0a82b.js","/pack/ebook.48bffc950a9d6db0a82b.js.map"],"nodejsScreencast":["/pack/nodejsScreencast.48bffc950a9d6db0a82b.js","/pack/nodejsScreencast.48bffc950a9d6db0a82b.js.map"],"profile":["/pack/profile.48bffc950a9d6db0a82b.js","/pack/profile.48bffc950a9d6db0a82b.js.map"],"coursesParticipantDetails":["/pack/coursesParticipantDetails.48bffc950a9d6db0a82b.js","/pack/coursesParticipantDetails.48bffc950a9d6db0a82b.js.map"],"about":["/pack/about.48bffc950a9d6db0a82b.js","/pack/about.1e00b1a06e928f6281912cb11b747e18.css","/pack/about.48bffc950a9d6db0a82b.js.map","/pack/about.1e00b1a06e928f6281912cb11b747e18.css.map"],"quiz":["/pack/quiz.48bffc950a9d6db0a82b.js","/pack/quiz.fe90633111dd089cf880c2bc10e2e44d.css","/pack/quiz.48bffc950a9d6db0a82b.js.map","/pack/quiz.fe90633111dd089cf880c2bc10e2e44d.css.map"],"head":["/pack/head.48bffc950a9d6db0a82b.js","/pack/head.fed95c071c1448d10f4ab76630bf208a.css","/pack/head.48bffc950a9d6db0a82b.js.map","/pack/head.fed95c071c1448d10f4ab76630bf208a.css.map"],"coursesMaterials":["/pack/coursesMaterials.48bffc950a9d6db0a82b.js","/pack/coursesMaterials.48bffc950a9d6db0a82b.js.map"],"auth":["/pack/auth.48bffc950a9d6db0a82b.js","/pack/auth.48bffc950a9d6db0a82b.js.map"],"coursesFrontpage":["/pack/coursesFrontpage.48bffc950a9d6db0a82b.js","/pack/coursesFrontpage.48bffc950a9d6db0a82b.js.map"],"coursesFeedbackEdit":["/pack/coursesFeedbackEdit.48bffc950a9d6db0a82b.js","/pack/coursesFeedbackEdit.48bffc950a9d6db0a82b.js.map"],"coursesFeedbackList":["/pack/coursesFeedbackList.48bffc950a9d6db0a82b.js","/pack/coursesFeedbackList.48bffc950a9d6db0a82b.js.map"],"coursesFeedbackShow":["/pack/coursesFeedbackShow.48bffc950a9d6db0a82b.js","/pack/coursesFeedbackShow.48bffc950a9d6db0a82b.js.map"],"profileGuestAboutMe":["/pack/profileGuestAboutMe.48bffc950a9d6db0a82b.js","/pack/profileGuestAboutMe.48bffc950a9d6db0a82b.js.map"],"webpackScreencast":["/pack/webpackScreencast.48bffc950a9d6db0a82b.js","/pack/webpackScreencast.48bffc950a9d6db0a82b.js.map"]}